{
    "_comment":  "Recovered Render export snapshot assembled from downloaded CSV files.",
    "_sources":  {
                     "sessions":  "sessions (5).csv",
                     "events":  "events (4).csv",
                     "answers":  "answers (9).csv",
                     "recoveredAt":  "2026-04-22T21:19:12+01:00"
                 },
    "sessions":  [
                     {
                         "id":  "0a2bf4fd-7471-4867-9d4d-4240291f6bf4",
                         "participantCode":  "11",
                         "group":  "ADHD",
                         "audioCondition":  "silence",
                         "createdAt":  "2026-02-27T14:28:15.680Z",
                         "endedAt":  null,
                         "score":  null
                     },
                     {
                         "id":  "310df6b6-85dd-4b65-bbd7-b14aee9d977b",
                         "participantCode":  "1",
                         "group":  "ADHD",
                         "audioCondition":  "silence",
                         "createdAt":  "2026-02-27T15:17:46.994Z",
                         "endedAt":  "2026-02-27T15:17:56.269Z",
                         "score":  1
                     },
                     {
                         "id":  "ba5171fa-a3d5-4249-9a1f-c29d9c43c0ef",
                         "participantCode":  "2",
                         "group":  "ADHD",
                         "audioCondition":  "white",
                         "createdAt":  "2026-02-27T15:21:11.430Z",
                         "endedAt":  "2026-02-27T15:21:23.675Z",
                         "score":  3
                     },
                     {
                         "id":  "6cbcde8a-8f31-413c-8a75-0fbf8363fb23",
                         "participantCode":  "1",
                         "group":  "ADHD",
                         "audioCondition":  "silence",
                         "createdAt":  "2026-02-27T16:10:49.991Z",
                         "endedAt":  "2026-02-27T16:10:54.429Z",
                         "score":  1
                     },
                     {
                         "id":  "2bd4bd17-f70d-40a0-87db-c996fe48658b",
                         "participantCode":  "1",
                         "group":  "Control",
                         "audioCondition":  "silence",
                         "createdAt":  "2026-03-03T12:04:06.115Z",
                         "endedAt":  null,
                         "score":  null
                     },
                     {
                         "id":  "e055a38c-cb9b-424c-bd72-1ca28df386ca",
                         "participantCode":  "1",
                         "group":  "Control",
                         "audioCondition":  "silence",
                         "createdAt":  "2026-03-07T15:16:15.167Z",
                         "endedAt":  "2026-03-07T15:16:22.198Z",
                         "score":  0
                     },
                     {
                         "id":  "e675b7fd-eb55-480f-82bd-3a8dc74ddc5a",
                         "participantCode":  "1",
                         "group":  "ADHD",
                         "audioCondition":  "silence",
                         "createdAt":  "2026-03-24T14:38:40.637Z",
                         "endedAt":  null,
                         "score":  null
                     },
                     {
                         "id":  "694fced4-583c-4301-9707-f14babfbfaa4",
                         "participantCode":  "1",
                         "group":  "ADHD",
                         "audioCondition":  "silence",
                         "createdAt":  "2026-03-24T15:01:27.367Z",
                         "endedAt":  "2026-03-24T15:01:36.042Z",
                         "score":  3
                     },
                     {
                         "id":  "8dbbdb25-a067-4523-a361-18d865681bd7",
                         "participantCode":  "67",
                         "group":  "ADHD",
                         "audioCondition":  "egyptian",
                         "createdAt":  "2026-03-24T16:29:25.317Z",
                         "endedAt":  "2026-03-24T16:29:59.116Z",
                         "score":  3
                     },
                     {
                         "id":  "025a6eb6-c92f-4f64-87ee-c81f0e88a32b",
                         "participantCode":  "1",
                         "group":  "ADHD",
                         "audioCondition":  "silence",
                         "createdAt":  "2026-04-21T21:58:33.367Z",
                         "endedAt":  "2026-04-21T21:58:53.479Z",
                         "score":  2
                     },
                     {
                         "id":  "e14c3200-26ea-40dd-8b29-10883c3f9b1d",
                         "participantCode":  "1",
                         "group":  "ADHD",
                         "audioCondition":  "silence",
                         "createdAt":  "2026-04-22T16:06:07.077Z",
                         "endedAt":  null,
                         "score":  null
                     },
                     {
                         "id":  "df34c93a-9160-4e15-983b-dd86a558c309",
                         "participantCode":  "999999999999999999999",
                         "group":  "ADHD",
                         "audioCondition":  "silence",
                         "createdAt":  "2026-04-22T17:33:22.172Z",
                         "endedAt":  "2026-04-22T17:33:44.614Z",
                         "score":  2
                     },
                     {
                         "id":  "5f35e349-5424-4c1f-be9d-aca325049deb",
                         "participantCode":  "1",
                         "group":  "ADHD",
                         "audioCondition":  "egyptian",
                         "createdAt":  "2026-04-22T17:40:03.533Z",
                         "endedAt":  "2026-04-22T17:44:48.445Z",
                         "score":  7
                     }
                 ],
    "events":  [
                   {
                       "id":  "32ef3062-079a-448a-a3ef-deffc1fd304f",
                       "sessionId":  "8dbbdb25-a067-4523-a361-18d865681bd7",
                       "sceneId":  "left",
                       "hotspotId":  "desert-edge",
                       "createdAt":  "2026-03-24T16:29:26.122Z"
                   },
                   {
                       "id":  "435743ab-caf8-44dd-9fd1-0e26f2a6a865",
                       "sessionId":  "8dbbdb25-a067-4523-a361-18d865681bd7",
                       "sceneId":  "left",
                       "hotspotId":  "great-pyramid",
                       "createdAt":  "2026-03-24T16:29:27.321Z"
                   },
                   {
                       "id":  "11576260-41a3-4c6a-b097-dc188ee86ff0",
                       "sessionId":  "8dbbdb25-a067-4523-a361-18d865681bd7",
                       "sceneId":  "left",
                       "hotspotId":  "sphinx",
                       "createdAt":  "2026-03-24T16:29:27.793Z"
                   },
                   {
                       "id":  "21ec1f8f-b036-4c9d-b61c-bdc912ae8fcf",
                       "sessionId":  "8dbbdb25-a067-4523-a361-18d865681bd7",
                       "sceneId":  "left",
                       "hotspotId":  "workers",
                       "createdAt":  "2026-03-24T16:29:28.314Z"
                   },
                   {
                       "id":  "920b8763-e6c6-469d-b753-6e7e6c45ee3b",
                       "sessionId":  "8dbbdb25-a067-4523-a361-18d865681bd7",
                       "sceneId":  "center",
                       "hotspotId":  "farming",
                       "createdAt":  "2026-03-24T16:29:28.841Z"
                   },
                   {
                       "id":  "f2117c78-a32e-4ab8-a55d-a554ccb7dc48",
                       "sessionId":  "8dbbdb25-a067-4523-a361-18d865681bd7",
                       "sceneId":  "center",
                       "hotspotId":  "wildlife",
                       "createdAt":  "2026-03-24T16:29:29.617Z"
                   },
                   {
                       "id":  "befeacbd-bc9c-4bbf-949c-8e429881d736",
                       "sessionId":  "8dbbdb25-a067-4523-a361-18d865681bd7",
                       "sceneId":  "center",
                       "hotspotId":  "boats",
                       "createdAt":  "2026-03-24T16:29:30.147Z"
                   },
                   {
                       "id":  "99346e04-f80d-4073-b300-c5240d329dec",
                       "sessionId":  "8dbbdb25-a067-4523-a361-18d865681bd7",
                       "sceneId":  "center",
                       "hotspotId":  "flooding",
                       "createdAt":  "2026-03-24T16:29:31.228Z"
                   },
                   {
                       "id":  "288cbcff-9383-417a-88f7-bf3d98d86cf5",
                       "sessionId":  "8dbbdb25-a067-4523-a361-18d865681bd7",
                       "sceneId":  "right",
                       "hotspotId":  "offerings",
                       "createdAt":  "2026-03-24T16:29:32.313Z"
                   },
                   {
                       "id":  "fef8025c-5776-4c41-aaf9-2517e7f7154c",
                       "sessionId":  "8dbbdb25-a067-4523-a361-18d865681bd7",
                       "sceneId":  "right",
                       "hotspotId":  "wall-paintings",
                       "createdAt":  "2026-03-24T16:29:33.017Z"
                   },
                   {
                       "id":  "81fb7050-842e-4c7a-8764-5e55d470a53f",
                       "sessionId":  "8dbbdb25-a067-4523-a361-18d865681bd7",
                       "sceneId":  "right",
                       "hotspotId":  "statues",
                       "createdAt":  "2026-03-24T16:29:33.426Z"
                   },
                   {
                       "id":  "a06ac689-4967-4b5e-bcc4-b6f8e8e7589a",
                       "sessionId":  "8dbbdb25-a067-4523-a361-18d865681bd7",
                       "sceneId":  "right",
                       "hotspotId":  "priests",
                       "createdAt":  "2026-03-24T16:29:34.112Z"
                   },
                   {
                       "id":  "2b5ffefe-60ed-4c96-adf0-bec0fce8271d",
                       "sessionId":  "025a6eb6-c92f-4f64-87ee-c81f0e88a32b",
                       "sceneId":  "left",
                       "hotspotId":  "workers",
                       "createdAt":  "2026-04-21T21:58:34.215Z"
                   },
                   {
                       "id":  "b8103299-66e8-4eda-aa84-31eda07feca1",
                       "sessionId":  "025a6eb6-c92f-4f64-87ee-c81f0e88a32b",
                       "sceneId":  "left",
                       "hotspotId":  "desert-edge",
                       "createdAt":  "2026-04-21T21:58:34.970Z"
                   },
                   {
                       "id":  "374c37ff-da2d-4a65-acc7-e6092bb2345b",
                       "sessionId":  "025a6eb6-c92f-4f64-87ee-c81f0e88a32b",
                       "sceneId":  "left",
                       "hotspotId":  "great-pyramid",
                       "createdAt":  "2026-04-21T21:58:39.332Z"
                   },
                   {
                       "id":  "a4238ffb-bc56-4fea-9399-ef7b7f056ad3",
                       "sessionId":  "025a6eb6-c92f-4f64-87ee-c81f0e88a32b",
                       "sceneId":  "center",
                       "hotspotId":  "flooding",
                       "createdAt":  "2026-04-21T21:58:40.499Z"
                   },
                   {
                       "id":  "faf118da-1712-49a6-a816-42e79a59e150",
                       "sessionId":  "e14c3200-26ea-40dd-8b29-10883c3f9b1d",
                       "sceneId":  "center",
                       "hotspotId":  "farming",
                       "createdAt":  "2026-04-22T16:06:08.226Z"
                   },
                   {
                       "id":  "5b4a68a1-ea63-473e-bd53-ffa7c7dba303",
                       "sessionId":  "e14c3200-26ea-40dd-8b29-10883c3f9b1d",
                       "sceneId":  "center",
                       "hotspotId":  "flooding",
                       "createdAt":  "2026-04-22T16:06:09.441Z"
                   },
                   {
                       "id":  "9378153c-97f9-40d9-a1e9-c0f65513670b",
                       "sessionId":  "e14c3200-26ea-40dd-8b29-10883c3f9b1d",
                       "sceneId":  "center",
                       "hotspotId":  "boats",
                       "createdAt":  "2026-04-22T16:06:10.627Z"
                   },
                   {
                       "id":  "b2e20353-70c1-4b91-a953-dcec82cb1142",
                       "sessionId":  "e14c3200-26ea-40dd-8b29-10883c3f9b1d",
                       "sceneId":  "center",
                       "hotspotId":  "wildlife",
                       "createdAt":  "2026-04-22T16:06:11.266Z"
                   },
                   {
                       "id":  "e9723374-24ba-47d3-98f4-ef068500e416",
                       "sessionId":  "e14c3200-26ea-40dd-8b29-10883c3f9b1d",
                       "sceneId":  "left",
                       "hotspotId":  "great-pyramid",
                       "createdAt":  "2026-04-22T16:06:12.260Z"
                   },
                   {
                       "id":  "a69d9663-ff61-4b83-88bf-5b03a90921c4",
                       "sessionId":  "e14c3200-26ea-40dd-8b29-10883c3f9b1d",
                       "sceneId":  "left",
                       "hotspotId":  "sphinx",
                       "createdAt":  "2026-04-22T16:06:14.498Z"
                   },
                   {
                       "id":  "b1fa0cd2-b2bd-4d17-b718-5c5e8b188370",
                       "sessionId":  "e14c3200-26ea-40dd-8b29-10883c3f9b1d",
                       "sceneId":  "left",
                       "hotspotId":  "workers",
                       "createdAt":  "2026-04-22T16:06:15.976Z"
                   },
                   {
                       "id":  "d03d445c-2edd-4cc0-a560-a4bee9aa7bf2",
                       "sessionId":  "e14c3200-26ea-40dd-8b29-10883c3f9b1d",
                       "sceneId":  "left",
                       "hotspotId":  "desert-edge",
                       "createdAt":  "2026-04-22T16:06:16.472Z"
                   },
                   {
                       "id":  "1e19e413-ea5e-471a-930d-03c0afca798e",
                       "sessionId":  "e14c3200-26ea-40dd-8b29-10883c3f9b1d",
                       "sceneId":  "right",
                       "hotspotId":  "offerings",
                       "createdAt":  "2026-04-22T16:06:17.698Z"
                   },
                   {
                       "id":  "e967fc52-0af1-4103-949f-624b3751a2c8",
                       "sessionId":  "e14c3200-26ea-40dd-8b29-10883c3f9b1d",
                       "sceneId":  "right",
                       "hotspotId":  "wall-paintings",
                       "createdAt":  "2026-04-22T16:06:18.769Z"
                   },
                   {
                       "id":  "2ce6e6e2-efdc-4dd3-98ac-a4e4ca39b6f4",
                       "sessionId":  "e14c3200-26ea-40dd-8b29-10883c3f9b1d",
                       "sceneId":  "right",
                       "hotspotId":  "priests",
                       "createdAt":  "2026-04-22T16:06:19.785Z"
                   },
                   {
                       "id":  "beef5c4a-c2b3-46d7-8ac0-f1afe83190b2",
                       "sessionId":  "e14c3200-26ea-40dd-8b29-10883c3f9b1d",
                       "sceneId":  "right",
                       "hotspotId":  "statues",
                       "createdAt":  "2026-04-22T16:06:20.418Z"
                   },
                   {
                       "id":  "8bf2aa4e-9b76-47db-a77d-3b79ddcc099a",
                       "sessionId":  "e14c3200-26ea-40dd-8b29-10883c3f9b1d",
                       "sceneId":  "right",
                       "hotspotId":  "priests",
                       "createdAt":  "2026-04-22T16:06:21.234Z"
                   },
                   {
                       "id":  "47f3b5f4-e1cf-4d76-8b52-f9d62a0837b8",
                       "sessionId":  "e14c3200-26ea-40dd-8b29-10883c3f9b1d",
                       "sceneId":  "left",
                       "hotspotId":  "great-pyramid",
                       "createdAt":  "2026-04-22T16:07:36.332Z"
                   },
                   {
                       "id":  "ad0fe81f-c9a8-4133-b660-47dcae4e6cce",
                       "sessionId":  "e14c3200-26ea-40dd-8b29-10883c3f9b1d",
                       "sceneId":  "left",
                       "hotspotId":  "sphinx",
                       "createdAt":  "2026-04-22T16:07:37.545Z"
                   },
                   {
                       "id":  "92762d57-350a-41bc-92f3-e8c70e13b068",
                       "sessionId":  "e14c3200-26ea-40dd-8b29-10883c3f9b1d",
                       "sceneId":  "left",
                       "hotspotId":  "workers",
                       "createdAt":  "2026-04-22T16:07:38.625Z"
                   },
                   {
                       "id":  "4d7064f4-d7ed-4169-8398-b5c7085b4f43",
                       "sessionId":  "e14c3200-26ea-40dd-8b29-10883c3f9b1d",
                       "sceneId":  "left",
                       "hotspotId":  "desert-edge",
                       "createdAt":  "2026-04-22T16:07:39.163Z"
                   },
                   {
                       "id":  "38a3485f-6921-47b9-af78-ab14c23a0725",
                       "sessionId":  "e14c3200-26ea-40dd-8b29-10883c3f9b1d",
                       "sceneId":  "center",
                       "hotspotId":  "farming",
                       "createdAt":  "2026-04-22T16:07:40.209Z"
                   },
                   {
                       "id":  "9568ac05-591b-4285-89c0-3c8878f0742a",
                       "sessionId":  "e14c3200-26ea-40dd-8b29-10883c3f9b1d",
                       "sceneId":  "left",
                       "hotspotId":  "great-pyramid",
                       "createdAt":  "2026-04-22T16:07:47.452Z"
                   },
                   {
                       "id":  "e503de33-5175-42a5-849b-a4238f29203a",
                       "sessionId":  "e14c3200-26ea-40dd-8b29-10883c3f9b1d",
                       "sceneId":  "left",
                       "hotspotId":  "sphinx",
                       "createdAt":  "2026-04-22T16:07:48.136Z"
                   },
                   {
                       "id":  "57616bfb-86d8-4de4-a46a-44b6c557d07a",
                       "sessionId":  "e14c3200-26ea-40dd-8b29-10883c3f9b1d",
                       "sceneId":  "left",
                       "hotspotId":  "workers",
                       "createdAt":  "2026-04-22T16:07:49.250Z"
                   },
                   {
                       "id":  "152cd250-47a4-40e5-8c41-7f157b093543",
                       "sessionId":  "e14c3200-26ea-40dd-8b29-10883c3f9b1d",
                       "sceneId":  "left",
                       "hotspotId":  "desert-edge",
                       "createdAt":  "2026-04-22T16:07:49.761Z"
                   },
                   {
                       "id":  "4412a818-ab61-4ee8-899b-ae15f65b86ee",
                       "sessionId":  "e14c3200-26ea-40dd-8b29-10883c3f9b1d",
                       "sceneId":  "center",
                       "hotspotId":  "farming",
                       "createdAt":  "2026-04-22T16:07:50.377Z"
                   },
                   {
                       "id":  "3e61bdf9-0a48-4514-bb23-01b5cdd163dc",
                       "sessionId":  "e14c3200-26ea-40dd-8b29-10883c3f9b1d",
                       "sceneId":  "center",
                       "hotspotId":  "flooding",
                       "createdAt":  "2026-04-22T16:07:51.209Z"
                   },
                   {
                       "id":  "ee43fe9f-df01-457f-9ad8-2ef39a346eeb",
                       "sessionId":  "e14c3200-26ea-40dd-8b29-10883c3f9b1d",
                       "sceneId":  "center",
                       "hotspotId":  "boats",
                       "createdAt":  "2026-04-22T16:07:51.978Z"
                   },
                   {
                       "id":  "4c56c6c2-af7b-49e9-bc69-472190f36391",
                       "sessionId":  "e14c3200-26ea-40dd-8b29-10883c3f9b1d",
                       "sceneId":  "center",
                       "hotspotId":  "wildlife",
                       "createdAt":  "2026-04-22T16:07:52.737Z"
                   },
                   {
                       "id":  "f78f280a-18b3-4b72-b837-57a185e0354e",
                       "sessionId":  "e14c3200-26ea-40dd-8b29-10883c3f9b1d",
                       "sceneId":  "right",
                       "hotspotId":  "wall-paintings",
                       "createdAt":  "2026-04-22T16:07:54.050Z"
                   },
                   {
                       "id":  "f40b3a46-3314-4d02-89b7-4a1bd87b6d80",
                       "sessionId":  "e14c3200-26ea-40dd-8b29-10883c3f9b1d",
                       "sceneId":  "right",
                       "hotspotId":  "statues",
                       "createdAt":  "2026-04-22T16:07:56.409Z"
                   },
                   {
                       "id":  "a69630ac-e506-4fd2-8caa-ef1dcfc159d1",
                       "sessionId":  "e14c3200-26ea-40dd-8b29-10883c3f9b1d",
                       "sceneId":  "right",
                       "hotspotId":  "priests",
                       "createdAt":  "2026-04-22T16:07:56.801Z"
                   },
                   {
                       "id":  "b544e0a5-10e9-44c0-ad8c-d9966ffa843e",
                       "sessionId":  "e14c3200-26ea-40dd-8b29-10883c3f9b1d",
                       "sceneId":  "right",
                       "hotspotId":  "offerings",
                       "createdAt":  "2026-04-22T16:07:57.241Z"
                   },
                   {
                       "id":  "c5a1fbca-edbd-4c74-adc6-8189b2796a0b",
                       "sessionId":  "e14c3200-26ea-40dd-8b29-10883c3f9b1d",
                       "sceneId":  "left",
                       "hotspotId":  "great-pyramid",
                       "createdAt":  "2026-04-22T16:07:59.145Z"
                   },
                   {
                       "id":  "5ad27459-3612-4dcf-99c4-59212793ef11",
                       "sessionId":  "e14c3200-26ea-40dd-8b29-10883c3f9b1d",
                       "sceneId":  "left",
                       "hotspotId":  "sphinx",
                       "createdAt":  "2026-04-22T16:08:03.633Z"
                   },
                   {
                       "id":  "f668dd12-1482-4edf-92b0-751abc319ff5",
                       "sessionId":  "e14c3200-26ea-40dd-8b29-10883c3f9b1d",
                       "sceneId":  "left",
                       "hotspotId":  "great-pyramid",
                       "createdAt":  "2026-04-22T16:09:20.533Z"
                   },
                   {
                       "id":  "e36aad8b-a927-4300-98f7-52f5f748a738",
                       "sessionId":  "e14c3200-26ea-40dd-8b29-10883c3f9b1d",
                       "sceneId":  "left",
                       "hotspotId":  "sphinx",
                       "createdAt":  "2026-04-22T16:09:21.977Z"
                   },
                   {
                       "id":  "0c738de2-b6c6-4ef3-94a8-532efc451d91",
                       "sessionId":  "e14c3200-26ea-40dd-8b29-10883c3f9b1d",
                       "sceneId":  "left",
                       "hotspotId":  "workers",
                       "createdAt":  "2026-04-22T16:09:23.363Z"
                   },
                   {
                       "id":  "8580cdb6-fcff-4009-84f2-5cb52af08fc4",
                       "sessionId":  "e14c3200-26ea-40dd-8b29-10883c3f9b1d",
                       "sceneId":  "left",
                       "hotspotId":  "desert-edge",
                       "createdAt":  "2026-04-22T16:09:24.067Z"
                   },
                   {
                       "id":  "0b553370-4242-4ced-b934-cf8da9efccec",
                       "sessionId":  "e14c3200-26ea-40dd-8b29-10883c3f9b1d",
                       "sceneId":  "center",
                       "hotspotId":  "farming",
                       "createdAt":  "2026-04-22T16:09:25.098Z"
                   },
                   {
                       "id":  "1bd67b65-520b-4601-8412-f4bcebcbab0e",
                       "sessionId":  "e14c3200-26ea-40dd-8b29-10883c3f9b1d",
                       "sceneId":  "center",
                       "hotspotId":  "flooding",
                       "createdAt":  "2026-04-22T16:09:25.987Z"
                   },
                   {
                       "id":  "894a254a-06a2-4dea-a742-3db08d34814b",
                       "sessionId":  "e14c3200-26ea-40dd-8b29-10883c3f9b1d",
                       "sceneId":  "center",
                       "hotspotId":  "wildlife",
                       "createdAt":  "2026-04-22T16:09:26.459Z"
                   },
                   {
                       "id":  "950d9418-7f90-4916-aab2-4b6d14b0ef75",
                       "sessionId":  "e14c3200-26ea-40dd-8b29-10883c3f9b1d",
                       "sceneId":  "center",
                       "hotspotId":  "boats",
                       "createdAt":  "2026-04-22T16:09:26.993Z"
                   },
                   {
                       "id":  "9e2d8f9e-53fc-4e28-a77e-a6db8d5013a3",
                       "sessionId":  "e14c3200-26ea-40dd-8b29-10883c3f9b1d",
                       "sceneId":  "right",
                       "hotspotId":  "offerings",
                       "createdAt":  "2026-04-22T16:09:27.746Z"
                   },
                   {
                       "id":  "d112b811-3785-4ccf-a2c8-ad0f8f121fed",
                       "sessionId":  "e14c3200-26ea-40dd-8b29-10883c3f9b1d",
                       "sceneId":  "right",
                       "hotspotId":  "wall-paintings",
                       "createdAt":  "2026-04-22T16:09:29.091Z"
                   },
                   {
                       "id":  "d142d87a-aba4-4ee1-89d0-aa76af011e36",
                       "sessionId":  "e14c3200-26ea-40dd-8b29-10883c3f9b1d",
                       "sceneId":  "right",
                       "hotspotId":  "statues",
                       "createdAt":  "2026-04-22T16:09:30.146Z"
                   },
                   {
                       "id":  "1a0e3436-f655-4b5b-85d1-6aa386721172",
                       "sessionId":  "e14c3200-26ea-40dd-8b29-10883c3f9b1d",
                       "sceneId":  "right",
                       "hotspotId":  "priests",
                       "createdAt":  "2026-04-22T16:09:30.953Z"
                   },
                   {
                       "id":  "4b4869b5-8a14-46d5-bbb4-1733edb56698",
                       "sessionId":  "e14c3200-26ea-40dd-8b29-10883c3f9b1d",
                       "sceneId":  "left",
                       "hotspotId":  "great-pyramid",
                       "createdAt":  "2026-04-22T16:09:32.308Z"
                   },
                   {
                       "id":  "eff98170-83dc-4f10-8463-baaa00c78a03",
                       "sessionId":  "e14c3200-26ea-40dd-8b29-10883c3f9b1d",
                       "sceneId":  "left",
                       "hotspotId":  "sphinx",
                       "createdAt":  "2026-04-22T16:10:40.370Z"
                   },
                   {
                       "id":  "439a8922-34ca-49d7-a07f-66b95f9b5f84",
                       "sessionId":  "e14c3200-26ea-40dd-8b29-10883c3f9b1d",
                       "sceneId":  "left",
                       "hotspotId":  "workers",
                       "createdAt":  "2026-04-22T16:10:41.185Z"
                   },
                   {
                       "id":  "919ea763-a31a-4cba-ad1b-1a20c237e686",
                       "sessionId":  "e14c3200-26ea-40dd-8b29-10883c3f9b1d",
                       "sceneId":  "left",
                       "hotspotId":  "desert-edge",
                       "createdAt":  "2026-04-22T16:10:41.730Z"
                   },
                   {
                       "id":  "061d8c56-2cf4-4869-ad39-73ed7d4d16ff",
                       "sessionId":  "e14c3200-26ea-40dd-8b29-10883c3f9b1d",
                       "sceneId":  "center",
                       "hotspotId":  "farming",
                       "createdAt":  "2026-04-22T16:10:42.817Z"
                   },
                   {
                       "id":  "21f0aa1c-dd9f-41b9-9347-721146cb1515",
                       "sessionId":  "e14c3200-26ea-40dd-8b29-10883c3f9b1d",
                       "sceneId":  "center",
                       "hotspotId":  "flooding",
                       "createdAt":  "2026-04-22T16:10:43.690Z"
                   },
                   {
                       "id":  "d29670af-78de-460e-9c38-61330a7302ea",
                       "sessionId":  "e14c3200-26ea-40dd-8b29-10883c3f9b1d",
                       "sceneId":  "center",
                       "hotspotId":  "wildlife",
                       "createdAt":  "2026-04-22T16:10:44.411Z"
                   },
                   {
                       "id":  "dda216db-dc31-40f0-8566-c61085f22f56",
                       "sessionId":  "e14c3200-26ea-40dd-8b29-10883c3f9b1d",
                       "sceneId":  "center",
                       "hotspotId":  "boats",
                       "createdAt":  "2026-04-22T16:10:45.659Z"
                   },
                   {
                       "id":  "8a61b273-03cb-410e-99cc-f689f6389bde",
                       "sessionId":  "e14c3200-26ea-40dd-8b29-10883c3f9b1d",
                       "sceneId":  "right",
                       "hotspotId":  "wall-paintings",
                       "createdAt":  "2026-04-22T16:10:46.762Z"
                   },
                   {
                       "id":  "850063a2-26ed-491a-86db-20742e26b36f",
                       "sessionId":  "e14c3200-26ea-40dd-8b29-10883c3f9b1d",
                       "sceneId":  "right",
                       "hotspotId":  "statues",
                       "createdAt":  "2026-04-22T16:10:47.770Z"
                   },
                   {
                       "id":  "7d02c2e0-4be5-4bdf-b7b0-41520ac5bca6",
                       "sessionId":  "e14c3200-26ea-40dd-8b29-10883c3f9b1d",
                       "sceneId":  "right",
                       "hotspotId":  "priests",
                       "createdAt":  "2026-04-22T16:10:48.754Z"
                   },
                   {
                       "id":  "1298e6f2-9bdc-4523-a728-7e62db416f31",
                       "sessionId":  "e14c3200-26ea-40dd-8b29-10883c3f9b1d",
                       "sceneId":  "right",
                       "hotspotId":  "offerings",
                       "createdAt":  "2026-04-22T16:10:49.562Z"
                   },
                   {
                       "id":  "d7c28f50-7804-48c7-82a3-ff0a67a4a1d9",
                       "sessionId":  "e14c3200-26ea-40dd-8b29-10883c3f9b1d",
                       "sceneId":  "left",
                       "hotspotId":  "great-pyramid",
                       "createdAt":  "2026-04-22T16:32:49.103Z"
                   },
                   {
                       "id":  "5d2580be-07a1-4ed6-83cd-90d869038b50",
                       "sessionId":  "e14c3200-26ea-40dd-8b29-10883c3f9b1d",
                       "sceneId":  "left",
                       "hotspotId":  "sphinx",
                       "createdAt":  "2026-04-22T16:32:49.829Z"
                   },
                   {
                       "id":  "57f91510-fad4-4cb1-8da7-202513a80e0d",
                       "sessionId":  "e14c3200-26ea-40dd-8b29-10883c3f9b1d",
                       "sceneId":  "left",
                       "hotspotId":  "workers",
                       "createdAt":  "2026-04-22T16:32:50.750Z"
                   },
                   {
                       "id":  "11d9b58f-23b3-473e-8393-3502c67342ae",
                       "sessionId":  "e14c3200-26ea-40dd-8b29-10883c3f9b1d",
                       "sceneId":  "left",
                       "hotspotId":  "desert-edge",
                       "createdAt":  "2026-04-22T16:32:51.942Z"
                   },
                   {
                       "id":  "da494382-f899-49e0-9656-bd5ecfcf943c",
                       "sessionId":  "e14c3200-26ea-40dd-8b29-10883c3f9b1d",
                       "sceneId":  "center",
                       "hotspotId":  "farming",
                       "createdAt":  "2026-04-22T16:32:52.508Z"
                   },
                   {
                       "id":  "8b5f1f08-309f-4de6-9790-e2fe141ee6a0",
                       "sessionId":  "e14c3200-26ea-40dd-8b29-10883c3f9b1d",
                       "sceneId":  "center",
                       "hotspotId":  "flooding",
                       "createdAt":  "2026-04-22T16:32:52.966Z"
                   },
                   {
                       "id":  "aee2a60f-7b57-4b79-930f-644af1d18ac4",
                       "sessionId":  "e14c3200-26ea-40dd-8b29-10883c3f9b1d",
                       "sceneId":  "center",
                       "hotspotId":  "wildlife",
                       "createdAt":  "2026-04-22T16:32:53.332Z"
                   },
                   {
                       "id":  "bcbb9e09-8824-4fa0-8941-2f3e8e3e42b4",
                       "sessionId":  "e14c3200-26ea-40dd-8b29-10883c3f9b1d",
                       "sceneId":  "center",
                       "hotspotId":  "boats",
                       "createdAt":  "2026-04-22T16:32:53.918Z"
                   },
                   {
                       "id":  "2d44705e-2aea-4def-82f3-4b33b569b213",
                       "sessionId":  "df34c93a-9160-4e15-983b-dd86a558c309",
                       "sceneId":  "left",
                       "hotspotId":  "workers",
                       "createdAt":  "2026-04-22T17:33:23.419Z"
                   },
                   {
                       "id":  "a9b70ed0-0881-451c-8415-a9e2074f773c",
                       "sessionId":  "df34c93a-9160-4e15-983b-dd86a558c309",
                       "sceneId":  "left",
                       "hotspotId":  "desert-edge",
                       "createdAt":  "2026-04-22T17:33:24.080Z"
                   },
                   {
                       "id":  "39f63697-02b4-4fcb-9125-f3f266148b3e",
                       "sessionId":  "df34c93a-9160-4e15-983b-dd86a558c309",
                       "sceneId":  "left",
                       "hotspotId":  "sphinx",
                       "createdAt":  "2026-04-22T17:33:24.806Z"
                   },
                   {
                       "id":  "2fa73b23-1599-49ae-869a-a0bf39c164db",
                       "sessionId":  "df34c93a-9160-4e15-983b-dd86a558c309",
                       "sceneId":  "left",
                       "hotspotId":  "great-pyramid",
                       "createdAt":  "2026-04-22T17:33:25.567Z"
                   },
                   {
                       "id":  "27eaf760-dbe3-4ae9-9d74-8a79ca0c9d4e",
                       "sessionId":  "df34c93a-9160-4e15-983b-dd86a558c309",
                       "sceneId":  "center",
                       "hotspotId":  "farming",
                       "createdAt":  "2026-04-22T17:33:26.575Z"
                   },
                   {
                       "id":  "ba2b9c4d-b61d-4f34-9924-417ebb913cb7",
                       "sessionId":  "df34c93a-9160-4e15-983b-dd86a558c309",
                       "sceneId":  "center",
                       "hotspotId":  "flooding",
                       "createdAt":  "2026-04-22T17:33:27.432Z"
                   },
                   {
                       "id":  "de14afa4-ab55-4889-acb6-8d9a4cd800d9",
                       "sessionId":  "df34c93a-9160-4e15-983b-dd86a558c309",
                       "sceneId":  "center",
                       "hotspotId":  "wildlife",
                       "createdAt":  "2026-04-22T17:33:27.733Z"
                   },
                   {
                       "id":  "83ef3601-95b1-422c-96be-b7b0a8d965cc",
                       "sessionId":  "df34c93a-9160-4e15-983b-dd86a558c309",
                       "sceneId":  "center",
                       "hotspotId":  "boats",
                       "createdAt":  "2026-04-22T17:33:28.444Z"
                   },
                   {
                       "id":  "9efea2ce-8d2b-4e29-9a2b-39d4d2a63941",
                       "sessionId":  "df34c93a-9160-4e15-983b-dd86a558c309",
                       "sceneId":  "right",
                       "hotspotId":  "wall-paintings",
                       "createdAt":  "2026-04-22T17:33:29.114Z"
                   },
                   {
                       "id":  "7789a7a2-d453-4107-98e8-1800bb5bdf73",
                       "sessionId":  "df34c93a-9160-4e15-983b-dd86a558c309",
                       "sceneId":  "right",
                       "hotspotId":  "statues",
                       "createdAt":  "2026-04-22T17:33:29.783Z"
                   },
                   {
                       "id":  "e7658dff-f9a6-46aa-8eb4-9cee1feea810",
                       "sessionId":  "df34c93a-9160-4e15-983b-dd86a558c309",
                       "sceneId":  "right",
                       "hotspotId":  "priests",
                       "createdAt":  "2026-04-22T17:33:30.123Z"
                   },
                   {
                       "id":  "f5989ad7-191a-4f43-ba86-05f6c36504a3",
                       "sessionId":  "df34c93a-9160-4e15-983b-dd86a558c309",
                       "sceneId":  "right",
                       "hotspotId":  "offerings",
                       "createdAt":  "2026-04-22T17:33:30.653Z"
                   },
                   {
                       "id":  "3b31c700-f855-49f3-ab67-af0de66c4b9f",
                       "sessionId":  "5f35e349-5424-4c1f-be9d-aca325049deb",
                       "sceneId":  "left",
                       "hotspotId":  "great-pyramid",
                       "createdAt":  "2026-04-22T17:40:19.512Z"
                   },
                   {
                       "id":  "668d09cf-7405-4f22-a37c-5ff3414962e2",
                       "sessionId":  "5f35e349-5424-4c1f-be9d-aca325049deb",
                       "sceneId":  "left",
                       "hotspotId":  "great-pyramid",
                       "createdAt":  "2026-04-22T17:40:23.135Z"
                   },
                   {
                       "id":  "3fb107a1-3e61-4918-b8fb-9a9c85a3070b",
                       "sessionId":  "5f35e349-5424-4c1f-be9d-aca325049deb",
                       "sceneId":  "left",
                       "hotspotId":  "sphinx",
                       "createdAt":  "2026-04-22T17:40:27.916Z"
                   },
                   {
                       "id":  "7a414fe8-d941-4420-b465-c28f34da144b",
                       "sessionId":  "5f35e349-5424-4c1f-be9d-aca325049deb",
                       "sceneId":  "left",
                       "hotspotId":  "great-pyramid",
                       "createdAt":  "2026-04-22T17:40:29.077Z"
                   },
                   {
                       "id":  "04c9c22a-ee28-483b-be1d-3891efac5fa8",
                       "sessionId":  "5f35e349-5424-4c1f-be9d-aca325049deb",
                       "sceneId":  "left",
                       "hotspotId":  "sphinx",
                       "createdAt":  "2026-04-22T17:40:41.748Z"
                   },
                   {
                       "id":  "d00d0ec5-709a-42a0-ad28-fefde074ef02",
                       "sessionId":  "5f35e349-5424-4c1f-be9d-aca325049deb",
                       "sceneId":  "left",
                       "hotspotId":  "workers",
                       "createdAt":  "2026-04-22T17:40:48.322Z"
                   },
                   {
                       "id":  "253b8640-8193-4e2e-b026-9a4c75a4c594",
                       "sessionId":  "5f35e349-5424-4c1f-be9d-aca325049deb",
                       "sceneId":  "left",
                       "hotspotId":  "desert-edge",
                       "createdAt":  "2026-04-22T17:41:11.327Z"
                   },
                   {
                       "id":  "23ebe20e-26db-4756-9dff-0da025736acd",
                       "sessionId":  "5f35e349-5424-4c1f-be9d-aca325049deb",
                       "sceneId":  "center",
                       "hotspotId":  "farming",
                       "createdAt":  "2026-04-22T17:41:25.880Z"
                   },
                   {
                       "id":  "89b798e9-85f3-4fec-909a-a59295dde965",
                       "sessionId":  "5f35e349-5424-4c1f-be9d-aca325049deb",
                       "sceneId":  "center",
                       "hotspotId":  "flooding",
                       "createdAt":  "2026-04-22T17:41:38.372Z"
                   },
                   {
                       "id":  "2cd7e772-05d1-41ff-bc33-92d03c785a11",
                       "sessionId":  "5f35e349-5424-4c1f-be9d-aca325049deb",
                       "sceneId":  "center",
                       "hotspotId":  "wildlife",
                       "createdAt":  "2026-04-22T17:41:45.732Z"
                   },
                   {
                       "id":  "6c3ee40b-4284-44b8-b897-029e8d85fc17",
                       "sessionId":  "5f35e349-5424-4c1f-be9d-aca325049deb",
                       "sceneId":  "center",
                       "hotspotId":  "boats",
                       "createdAt":  "2026-04-22T17:41:53.345Z"
                   },
                   {
                       "id":  "717dfaf8-dec5-4799-8cfb-5ee0fe797584",
                       "sessionId":  "5f35e349-5424-4c1f-be9d-aca325049deb",
                       "sceneId":  "right",
                       "hotspotId":  "wall-paintings",
                       "createdAt":  "2026-04-22T17:42:01.511Z"
                   },
                   {
                       "id":  "5241ff88-c665-44c1-9139-a2e6a25a0908",
                       "sessionId":  "5f35e349-5424-4c1f-be9d-aca325049deb",
                       "sceneId":  "right",
                       "hotspotId":  "statues",
                       "createdAt":  "2026-04-22T17:42:15.649Z"
                   },
                   {
                       "id":  "1748587d-daf6-4210-8d72-be7852f8d990",
                       "sessionId":  "5f35e349-5424-4c1f-be9d-aca325049deb",
                       "sceneId":  "right",
                       "hotspotId":  "priests",
                       "createdAt":  "2026-04-22T17:42:25.258Z"
                   },
                   {
                       "id":  "66cf2838-18ec-4b8b-87fe-fbdfdab31c9a",
                       "sessionId":  "5f35e349-5424-4c1f-be9d-aca325049deb",
                       "sceneId":  "right",
                       "hotspotId":  "offerings",
                       "createdAt":  "2026-04-22T17:42:32.428Z"
                   }
               ],
    "answers":  [
                    {
                        "id":  "3061b37d-2370-40c4-9813-169e76649fb5",
                        "sessionId":  "310df6b6-85dd-4b65-bbd7-b14aee9d977b",
                        "questionId":  "giza_q1",
                        "selectedIndex":  0,
                        "isCorrect":  false,
                        "responseTimeMs":  18088,
                        "createdAt":  "2026-02-27T15:17:53.587Z"
                    },
                    {
                        "id":  "75a2fbfa-e937-4e9c-ae2f-6fff7b4a2a09",
                        "sessionId":  "310df6b6-85dd-4b65-bbd7-b14aee9d977b",
                        "questionId":  "nile_q1",
                        "selectedIndex":  0,
                        "isCorrect":  true,
                        "responseTimeMs":  1404,
                        "createdAt":  "2026-02-27T15:17:54.998Z"
                    },
                    {
                        "id":  "cc68412f-ef25-436b-b5e6-d87ca3494c37",
                        "sessionId":  "310df6b6-85dd-4b65-bbd7-b14aee9d977b",
                        "questionId":  "giza_q2",
                        "selectedIndex":  1,
                        "isCorrect":  false,
                        "responseTimeMs":  1257,
                        "createdAt":  "2026-02-27T15:17:56.262Z"
                    },
                    {
                        "id":  "9e19a9a9-1b93-4816-90b9-23dad24c56be",
                        "sessionId":  "ba5171fa-a3d5-4249-9a1f-c29d9c43c0ef",
                        "questionId":  "giza_q1",
                        "selectedIndex":  1,
                        "isCorrect":  true,
                        "responseTimeMs":  8211,
                        "createdAt":  "2026-02-27T15:21:13.794Z"
                    },
                    {
                        "id":  "29494c8e-bd1c-4b76-bdd4-591a8ed8f947",
                        "sessionId":  "ba5171fa-a3d5-4249-9a1f-c29d9c43c0ef",
                        "questionId":  "nile_q1",
                        "selectedIndex":  0,
                        "isCorrect":  true,
                        "responseTimeMs":  4624,
                        "createdAt":  "2026-02-27T15:21:18.425Z"
                    },
                    {
                        "id":  "72872907-a8fb-42ae-9d1c-0d6e588d94d7",
                        "sessionId":  "ba5171fa-a3d5-4249-9a1f-c29d9c43c0ef",
                        "questionId":  "giza_q2",
                        "selectedIndex":  0,
                        "isCorrect":  true,
                        "responseTimeMs":  5225,
                        "createdAt":  "2026-02-27T15:21:23.657Z"
                    },
                    {
                        "id":  "624064d1-967a-4ca6-924a-a1babebd5845",
                        "sessionId":  "6cbcde8a-8f31-413c-8a75-0fbf8363fb23",
                        "questionId":  "giza_q1",
                        "selectedIndex":  1,
                        "isCorrect":  true,
                        "responseTimeMs":  7452,
                        "createdAt":  "2026-02-27T16:10:52.107Z"
                    },
                    {
                        "id":  "b710dae2-3474-46b1-8c0e-6e50ab7affb1",
                        "sessionId":  "6cbcde8a-8f31-413c-8a75-0fbf8363fb23",
                        "questionId":  "nile_q1",
                        "selectedIndex":  1,
                        "isCorrect":  false,
                        "responseTimeMs":  1166,
                        "createdAt":  "2026-02-27T16:10:53.278Z"
                    },
                    {
                        "id":  "c2577f29-901c-4252-a9e3-37c0bb0938ab",
                        "sessionId":  "6cbcde8a-8f31-413c-8a75-0fbf8363fb23",
                        "questionId":  "giza_q2",
                        "selectedIndex":  1,
                        "isCorrect":  false,
                        "responseTimeMs":  1135,
                        "createdAt":  "2026-02-27T16:10:54.424Z"
                    },
                    {
                        "id":  "f208d078-94e7-4b13-9560-db4c30b07604",
                        "sessionId":  "e055a38c-cb9b-424c-bd72-1ca28df386ca",
                        "questionId":  "giza_q1",
                        "selectedIndex":  2,
                        "isCorrect":  false,
                        "responseTimeMs":  14465,
                        "createdAt":  "2026-03-07T15:16:20.105Z"
                    },
                    {
                        "id":  "4e4221c6-e9e6-4ce2-b80a-ca21401cbe2a",
                        "sessionId":  "e055a38c-cb9b-424c-bd72-1ca28df386ca",
                        "questionId":  "nile_q1",
                        "selectedIndex":  2,
                        "isCorrect":  false,
                        "responseTimeMs":  1252,
                        "createdAt":  "2026-03-07T15:16:21.369Z"
                    },
                    {
                        "id":  "62e09887-1a30-4cfa-8408-baf75cb28857",
                        "sessionId":  "e055a38c-cb9b-424c-bd72-1ca28df386ca",
                        "questionId":  "giza_q2",
                        "selectedIndex":  2,
                        "isCorrect":  false,
                        "responseTimeMs":  810,
                        "createdAt":  "2026-03-07T15:16:22.191Z"
                    },
                    {
                        "id":  "d8f46c65-f05d-4c59-b1b2-94f3f6b766b8",
                        "sessionId":  "694fced4-583c-4301-9707-f14babfbfaa4",
                        "questionId":  "giza_q1",
                        "selectedIndex":  1,
                        "isCorrect":  true,
                        "responseTimeMs":  5036,
                        "createdAt":  "2026-03-24T15:01:29.373Z"
                    },
                    {
                        "id":  "c0768596-bd7e-4605-a105-35b10535037d",
                        "sessionId":  "694fced4-583c-4301-9707-f14babfbfaa4",
                        "questionId":  "nile_q1",
                        "selectedIndex":  0,
                        "isCorrect":  true,
                        "responseTimeMs":  3909,
                        "createdAt":  "2026-03-24T15:01:33.290Z"
                    },
                    {
                        "id":  "93bf9a91-b6d2-4a3e-ad5a-511b5642783f",
                        "sessionId":  "694fced4-583c-4301-9707-f14babfbfaa4",
                        "questionId":  "giza_q2",
                        "selectedIndex":  0,
                        "isCorrect":  true,
                        "responseTimeMs":  2737,
                        "createdAt":  "2026-03-24T15:01:36.033Z"
                    },
                    {
                        "id":  "028be02e-e20e-4412-8fac-7a6dadd2f7c5",
                        "sessionId":  "8dbbdb25-a067-4523-a361-18d865681bd7",
                        "questionId":  "q1_nile_civilisation",
                        "selectedIndex":  1,
                        "isCorrect":  false,
                        "responseTimeMs":  15929,
                        "createdAt":  "2026-03-24T16:29:52.561Z"
                    },
                    {
                        "id":  "c31feb85-57ff-42cf-ba41-7522b0709347",
                        "sessionId":  "8dbbdb25-a067-4523-a361-18d865681bd7",
                        "questionId":  "q2_pyramid_workers",
                        "selectedIndex":  0,
                        "isCorrect":  true,
                        "responseTimeMs":  1292,
                        "createdAt":  "2026-03-24T16:29:53.858Z"
                    },
                    {
                        "id":  "c3ac3d36-0573-47d9-abdc-cdabb612e14f",
                        "sessionId":  "8dbbdb25-a067-4523-a361-18d865681bd7",
                        "questionId":  "q3_nile_flooding",
                        "selectedIndex":  2,
                        "isCorrect":  true,
                        "responseTimeMs":  1193,
                        "createdAt":  "2026-03-24T16:29:55.055Z"
                    },
                    {
                        "id":  "0ab583ac-e860-474a-8a98-12a7bda48eee",
                        "sessionId":  "8dbbdb25-a067-4523-a361-18d865681bd7",
                        "questionId":  "q4_great_pyramid_power",
                        "selectedIndex":  2,
                        "isCorrect":  false,
                        "responseTimeMs":  922,
                        "createdAt":  "2026-03-24T16:29:55.984Z"
                    },
                    {
                        "id":  "cf5683c5-3c54-45ba-9519-0a4368571a4b",
                        "sessionId":  "8dbbdb25-a067-4523-a361-18d865681bd7",
                        "questionId":  "q5_temples_society",
                        "selectedIndex":  2,
                        "isCorrect":  true,
                        "responseTimeMs":  1049,
                        "createdAt":  "2026-03-24T16:29:57.039Z"
                    },
                    {
                        "id":  "89a37e1b-8a48-4a3e-bc57-98c071d64bad",
                        "sessionId":  "8dbbdb25-a067-4523-a361-18d865681bd7",
                        "questionId":  "q6_papyrus",
                        "selectedIndex":  2,
                        "isCorrect":  false,
                        "responseTimeMs":  1010,
                        "createdAt":  "2026-03-24T16:29:58.056Z"
                    },
                    {
                        "id":  "8a1db65e-71ef-4b1d-a257-76949ab414dd",
                        "sessionId":  "8dbbdb25-a067-4523-a361-18d865681bd7",
                        "questionId":  "q7_desert_location",
                        "selectedIndex":  2,
                        "isCorrect":  false,
                        "responseTimeMs":  1051,
                        "createdAt":  "2026-03-24T16:29:59.112Z"
                    },
                    {
                        "id":  "b8cbb0e6-e7f8-4e14-9695-bad4f3690952",
                        "sessionId":  "025a6eb6-c92f-4f64-87ee-c81f0e88a32b",
                        "questionId":  "q1_nile_civilisation",
                        "selectedIndex":  0,
                        "isCorrect":  false,
                        "responseTimeMs":  4672,
                        "createdAt":  "2026-04-21T21:58:45.853Z"
                    },
                    {
                        "id":  "60c8a0ea-d124-4ed7-866b-4220ac4a002d",
                        "sessionId":  "025a6eb6-c92f-4f64-87ee-c81f0e88a32b",
                        "questionId":  "q2_pyramid_workers",
                        "selectedIndex":  0,
                        "isCorrect":  true,
                        "responseTimeMs":  1232,
                        "createdAt":  "2026-04-21T21:58:47.090Z"
                    },
                    {
                        "id":  "f014763c-d241-43a2-afa7-48e62ccc9c58",
                        "sessionId":  "025a6eb6-c92f-4f64-87ee-c81f0e88a32b",
                        "questionId":  "q3_nile_flooding",
                        "selectedIndex":  0,
                        "isCorrect":  false,
                        "responseTimeMs":  1193,
                        "createdAt":  "2026-04-21T21:58:48.290Z"
                    },
                    {
                        "id":  "ed653b66-a450-4fb1-813b-ba2f05c55272",
                        "sessionId":  "025a6eb6-c92f-4f64-87ee-c81f0e88a32b",
                        "questionId":  "q4_great_pyramid_power",
                        "selectedIndex":  0,
                        "isCorrect":  false,
                        "responseTimeMs":  1250,
                        "createdAt":  "2026-04-21T21:58:49.547Z"
                    },
                    {
                        "id":  "b77be82f-081a-4a3f-a67c-c05a68e51b56",
                        "sessionId":  "025a6eb6-c92f-4f64-87ee-c81f0e88a32b",
                        "questionId":  "q5_temples_society",
                        "selectedIndex":  0,
                        "isCorrect":  false,
                        "responseTimeMs":  1057,
                        "createdAt":  "2026-04-21T21:58:50.619Z"
                    },
                    {
                        "id":  "3474116b-324f-4eee-a424-4cdf4e50e0dd",
                        "sessionId":  "025a6eb6-c92f-4f64-87ee-c81f0e88a32b",
                        "questionId":  "q6_papyrus",
                        "selectedIndex":  0,
                        "isCorrect":  false,
                        "responseTimeMs":  1748,
                        "createdAt":  "2026-04-21T21:58:52.377Z"
                    },
                    {
                        "id":  "be858d50-e3fa-496b-9a26-d72a5178c156",
                        "sessionId":  "025a6eb6-c92f-4f64-87ee-c81f0e88a32b",
                        "questionId":  "q7_desert_location",
                        "selectedIndex":  0,
                        "isCorrect":  true,
                        "responseTimeMs":  1091,
                        "createdAt":  "2026-04-21T21:58:53.473Z"
                    },
                    {
                        "id":  "246945ad-08d2-41f3-b9fb-7a71b99b7fab",
                        "sessionId":  "df34c93a-9160-4e15-983b-dd86a558c309",
                        "questionId":  "q1_nile_civilisation",
                        "selectedIndex":  0,
                        "isCorrect":  false,
                        "responseTimeMs":  6078,
                        "createdAt":  "2026-04-22T17:33:37.375Z"
                    },
                    {
                        "id":  "dc3f1b7e-b062-44c3-998f-2df16a00d386",
                        "sessionId":  "df34c93a-9160-4e15-983b-dd86a558c309",
                        "questionId":  "q2_pyramid_workers",
                        "selectedIndex":  0,
                        "isCorrect":  true,
                        "responseTimeMs":  952,
                        "createdAt":  "2026-04-22T17:33:38.523Z"
                    },
                    {
                        "id":  "50400b8b-9fc1-4fdf-8fa3-4313f43e3a65",
                        "sessionId":  "df34c93a-9160-4e15-983b-dd86a558c309",
                        "questionId":  "q3_nile_flooding",
                        "selectedIndex":  0,
                        "isCorrect":  false,
                        "responseTimeMs":  816,
                        "createdAt":  "2026-04-22T17:33:39.532Z"
                    },
                    {
                        "id":  "fc413f79-e153-4b3c-8c68-a889cb40a698",
                        "sessionId":  "df34c93a-9160-4e15-983b-dd86a558c309",
                        "questionId":  "q4_great_pyramid_power",
                        "selectedIndex":  0,
                        "isCorrect":  false,
                        "responseTimeMs":  1034,
                        "createdAt":  "2026-04-22T17:33:40.765Z"
                    },
                    {
                        "id":  "ca31bad6-405f-482a-b688-47234c48c439",
                        "sessionId":  "df34c93a-9160-4e15-983b-dd86a558c309",
                        "questionId":  "q5_temples_society",
                        "selectedIndex":  0,
                        "isCorrect":  false,
                        "responseTimeMs":  896,
                        "createdAt":  "2026-04-22T17:33:42.063Z"
                    },
                    {
                        "id":  "454d65ec-b4e0-442e-8a4e-9e35395d1640",
                        "sessionId":  "df34c93a-9160-4e15-983b-dd86a558c309",
                        "questionId":  "q6_papyrus",
                        "selectedIndex":  0,
                        "isCorrect":  false,
                        "responseTimeMs":  605,
                        "createdAt":  "2026-04-22T17:33:42.868Z"
                    },
                    {
                        "id":  "b2e09770-f472-4739-9005-ccc644cf897e",
                        "sessionId":  "df34c93a-9160-4e15-983b-dd86a558c309",
                        "questionId":  "q7_desert_location",
                        "selectedIndex":  0,
                        "isCorrect":  true,
                        "responseTimeMs":  1330,
                        "createdAt":  "2026-04-22T17:33:44.428Z"
                    },
                    {
                        "id":  "0e86e324-a8f3-4533-9b54-d75326831410",
                        "sessionId":  "5f35e349-5424-4c1f-be9d-aca325049deb",
                        "questionId":  "q1_nile_civilisation",
                        "selectedIndex":  2,
                        "isCorrect":  true,
                        "responseTimeMs":  25110,
                        "createdAt":  "2026-04-22T17:43:12.987Z"
                    },
                    {
                        "id":  "94b48c19-9ab0-4c09-ae23-fa820202967c",
                        "sessionId":  "5f35e349-5424-4c1f-be9d-aca325049deb",
                        "questionId":  "q2_pyramid_workers",
                        "selectedIndex":  0,
                        "isCorrect":  true,
                        "responseTimeMs":  15842,
                        "createdAt":  "2026-04-22T17:43:29.357Z"
                    },
                    {
                        "id":  "56d334f3-394e-4508-a13e-2c268c995e7d",
                        "sessionId":  "5f35e349-5424-4c1f-be9d-aca325049deb",
                        "questionId":  "q3_nile_flooding",
                        "selectedIndex":  2,
                        "isCorrect":  true,
                        "responseTimeMs":  9626,
                        "createdAt":  "2026-04-22T17:43:39.598Z"
                    },
                    {
                        "id":  "f73e02a8-0596-4b7b-bd4e-fe4465524faf",
                        "sessionId":  "5f35e349-5424-4c1f-be9d-aca325049deb",
                        "questionId":  "q4_great_pyramid_power",
                        "selectedIndex":  1,
                        "isCorrect":  true,
                        "responseTimeMs":  16384,
                        "createdAt":  "2026-04-22T17:43:56.498Z"
                    },
                    {
                        "id":  "aadb80bf-7c22-428a-bf21-42ac44ecd3a8",
                        "sessionId":  "5f35e349-5424-4c1f-be9d-aca325049deb",
                        "questionId":  "q5_temples_society",
                        "selectedIndex":  2,
                        "isCorrect":  true,
                        "responseTimeMs":  10659,
                        "createdAt":  "2026-04-22T17:44:07.769Z"
                    },
                    {
                        "id":  "00807c93-7f73-40f5-8ab7-2a370763a719",
                        "sessionId":  "5f35e349-5424-4c1f-be9d-aca325049deb",
                        "questionId":  "q6_papyrus",
                        "selectedIndex":  3,
                        "isCorrect":  true,
                        "responseTimeMs":  28661,
                        "createdAt":  "2026-04-22T17:44:36.952Z"
                    },
                    {
                        "id":  "735e56af-a9d5-4010-ae82-4d8b1ef0a651",
                        "sessionId":  "5f35e349-5424-4c1f-be9d-aca325049deb",
                        "questionId":  "q7_desert_location",
                        "selectedIndex":  0,
                        "isCorrect":  true,
                        "responseTimeMs":  10730,
                        "createdAt":  "2026-04-22T17:44:48.236Z"
                    }
                ]
}
